{"timezone": "Europe/Madrid", "state_code": "51", "country_code": "ES", "lat": 36.928026, "lon": -2.687309, "city_name": "F\u00e9lix", "station_id": "605400-99999", "data": [{"rh": 42, "wind_spd": 3.48038, "timestamp_utc": "2020-03-13T00:00:00", "vis": 5, "slp": 1019.95, "pod": "n", "dni": 0, "elev_angle": -55.72, "pres": 898.1, "h_angle": 90, "dewpt": -0.1, "snow": 0, "uv": 0, "solar_rad": 0, "wind_dir": 200, "weather": {"icon": "c04n", "code": 804, "description": "Overcast clouds"}, "ghi": 0, "dhi": 0, "timestamp_local": "2020-03-13T01:00:00", "app_temp": 14.5, "azimuth": 351.4, "datetime": "2020-03-13:00", "temp": 14.5, "precip": 0, "clouds": 100, "ts": 1584057600}, {"rh": 44, "wind_spd": 2.87726, "timestamp_utc": "2020-03-13T01:00:00", "vis": 5, "slp": 1019.93, "pod": "n", "dni": 0, "elev_angle": -54.73, "pres": 898.1, "h_angle": 90, "dewpt": -0.1, "snow": 0, "uv": 0, "solar_rad": 0, "wind_dir": 200, "weather": {"icon": "c04n", "code": 804, "description": "Overcast clouds"}, "ghi": 0, "dhi": 0, "timestamp_local": "2020-03-13T02:00:00", "app_temp": 13.8, "azimuth": 17.77, "datetime": "2020-03-13:01", "temp": 13.8, "precip": 0, "clouds": 100, "ts": 1584061200}, {"rh": 45, "wind_spd": 2.32565, "timestamp_utc": "2020-03-13T02:00:00", "vis": 5, "slp": 1019.79, "pod": "n", "dni": 0, "elev_angle": -48.84, "pres": 898.1, "h_angle": 90, "dewpt": -0.1, "snow": 0, "uv": 0, "solar_rad": 0, "wind_dir": 200, "weather": {"icon": "c04n", "code": 804, "description": "Overcast clouds"}, "ghi": 0, "dhi": 0, "timestamp_local": "2020-03-13T03:00:00", "app_temp": 13.1, "azimuth": 40.19, "datetime": "2020-03-13:02", "temp": 13.1, "precip": 0, "clouds": 100, "ts": 1584064800}, {"rh": 46, "wind_spd": 1.92679, "timestamp_utc": "2020-03-13T03:00:00", "vis": 5, "slp": 1019.86, "pod": "n", "dni": 0, "elev_angle": -39.8, "pres": 898.1, "h_angle": 90, "dewpt": -0.1, "snow": 0, "uv": 0, "solar_rad": 0, "wind_dir": 200, "weather": {"icon": "c04n", "code": 804, "description": "Overcast clouds"}, "ghi": 0, "dhi": 0, "timestamp_local": "2020-03-13T04:00:00", "app_temp": 12.8, "azimuth": 56.99, "datetime": "2020-03-13:03", "temp": 12.8, "precip": 0, "clouds": 100, "ts": 1584068400}, {"rh": 48, "wind_spd": 1.67025, "timestamp_utc": "2020-03-13T04:00:00", "vis": 5, "slp": 1019.5, "pod": "n", "dni": 0, "elev_angle": -29.05, "pres": 898.1, "h_angle": 90, "dewpt": -0.1, "snow": 0, "uv": 0, "solar_rad": 0, "wind_dir": 200, "weather": {"icon": "c04n", "code": 804, "description": "Overcast clouds"}, "ghi": 0, "dhi": 0, "timestamp_local": "2020-03-13T05:00:00", "app_temp": 12.2, "azimuth": 69.7, "datetime": "2020-03-13:04", "temp": 12.2, "precip": 0, "clouds": 100, "ts": 1584072000}, {"rh": 48, "wind_spd": 1.57832, "timestamp_utc": "2020-03-13T05:00:00", "vis": 5, "slp": 1019.42, "pod": "n", "dni": 0, "elev_angle": -17.46, "pres": 898.1, "h_angle": 90, "dewpt": -0.1, "snow": 0, "uv": 0, "solar_rad": 0, "wind_dir": 200, "weather": {"icon": "c04n", "code": 804, "description": "Overcast clouds"}, "ghi": 0, "dhi": 0, "timestamp_local": "2020-03-13T06:00:00", "app_temp": 11.5, "azimuth": 80.07, "datetime": "2020-03-13:05", "temp": 11.5, "precip": 0, "clouds": 100, "ts": 1584075600}, {"rh": 50, "wind_spd": 1.63562, "timestamp_utc": "2020-03-13T06:00:00", "vis": 5, "slp": 1019.72, "pod": "n", "dni": 0, "elev_angle": -5.5, "pres": 898.1, "h_angle": 90, "dewpt": -0.1, "snow": 0, "uv": 0, "solar_rad": 0, "wind_dir": 200, "weather": {"icon": "c04n", "code": 804, "description": "Overcast clouds"}, "ghi": 0, "dhi": 0, "timestamp_local": "2020-03-13T07:00:00", "app_temp": 11.1, "azimuth": 89.31, "datetime": "2020-03-13:06", "temp": 11.1, "precip": 0, "clouds": 100, "ts": 1584079200}, {"rh": 50, "wind_spd": 1.67152, "timestamp_utc": "2020-03-13T07:00:00", "vis": 5, "slp": 1023, "pod": "d", "dni": 361.5, "elev_angle": 6.47, "pres": 890.7, "h_angle": -90, "dewpt": -1.1, "snow": 0, "uv": 0.8, "solar_rad": 18.1825, "wind_dir": 210, "weather": {"icon": "c04d", "code": 804, "description": "Overcast clouds"}, "ghi": 72.73, "dhi": 41.23, "timestamp_local": "2020-03-13T08:00:00", "app_temp": 11.2, "azimuth": 98.33, "datetime": "2020-03-13:07", "temp": 11.2, "precip": 0, "clouds": 100, "ts": 1584082800}, {"rh": 43, "wind_spd": 2.3053, "timestamp_utc": "2020-03-13T08:00:00", "vis": 5, "slp": 1023, "pod": "d", "dni": 652.82, "elev_angle": 18.17, "pres": 890.7, "h_angle": -75, "dewpt": -0.3, "snow": 0, "uv": 1.2, "solar_rad": 67.7325, "wind_dir": 210, "weather": {"icon": "c04d", "code": 804, "description": "Overcast clouds"}, "ghi": 270.93, "dhi": 74.54, "timestamp_local": "2020-03-13T09:00:00", "app_temp": 13.1, "azimuth": 107.94, "datetime": "2020-03-13:08", "temp": 13.1, "precip": 0, "clouds": 100, "ts": 1584086400}, {"rh": 37, "wind_spd": 3.57016, "timestamp_utc": "2020-03-13T09:00:00", "vis": 5, "slp": 1023, "pod": "d", "dni": 783.25, "elev_angle": 29.19, "pres": 892.4, "h_angle": -75, "dewpt": -0.1, "snow": 0, "uv": 1.6, "solar_rad": 117.37, "wind_dir": 200, "weather": {"icon": "c04d", "code": 804, "description": "Overcast clouds"}, "ghi": 469.48, "dhi": 94.01, "timestamp_local": "2020-03-13T10:00:00", "app_temp": 15.2, "azimuth": 119.06, "datetime": "2020-03-13:09", "temp": 15.2, "precip": 0, "clouds": 100, "ts": 1584090000}, {"rh": 32, "wind_spd": 3.58069, "timestamp_utc": "2020-03-13T10:00:00", "vis": 5, "slp": 1023, "pod": "d", "dni": 854.26, "elev_angle": 38.93, "pres": 892.8, "h_angle": -45, "dewpt": -1.3, "snow": 0, "uv": 2, "solar_rad": 159.122, "wind_dir": 210, "weather": {"icon": "c04d", "code": 804, "description": "Overcast clouds"}, "ghi": 636.49, "dhi": 106.42, "timestamp_local": "2020-03-13T11:00:00", "app_temp": 17.3, "azimuth": 132.85, "datetime": "2020-03-13:10", "temp": 17.3, "precip": 0, "clouds": 100, "ts": 1584093600}, {"rh": 28, "wind_spd": 4.29556, "timestamp_utc": "2020-03-13T11:00:00", "vis": 5, "slp": 1018.24, "pod": "d", "dni": 892.77, "elev_angle": 46.42, "pres": 898.1, "h_angle": -30, "dewpt": -2.1, "snow": 0, "uv": 2.4, "solar_rad": 188.325, "wind_dir": 210, "weather": {"icon": "c04d", "code": 804, "description": "Overcast clouds"}, "ghi": 753.3, "dhi": 113.82, "timestamp_local": "2020-03-13T12:00:00", "app_temp": 17.5, "azimuth": 150.59, "datetime": "2020-03-13:11", "temp": 18.8, "precip": 0, "clouds": 100, "ts": 1584097200}, {"rh": 25, "wind_spd": 4.08274, "timestamp_utc": "2020-03-13T12:00:00", "vis": 5, "slp": 1023, "pod": "d", "dni": 908.68, "elev_angle": 50.27, "pres": 894.5, "h_angle": -30, "dewpt": -3.3, "snow": 0, "uv": 2.5, "solar_rad": 202.087, "wind_dir": 220, "weather": {"icon": "c04d", "code": 804, "description": "Overcast clouds"}, "ghi": 808.35, "dhi": 117.02, "timestamp_local": "2020-03-13T13:00:00", "app_temp": 19, "azimuth": 172.48, "datetime": "2020-03-13:12", "temp": 20.3, "precip": 0, "clouds": 100, "ts": 1584100800}, {"rh": 23, "wind_spd": 3.3593, "timestamp_utc": "2020-03-13T13:00:00", "vis": 5, "slp": 1022, "pod": "d", "dni": 905.34, "elev_angle": 49.41, "pres": 894.4, "h_angle": -15, "dewpt": -1.5, "snow": 0, "uv": 2.5, "solar_rad": 199.11, "wind_dir": 230, "weather": {"icon": "c04d", "code": 804, "description": "Overcast clouds"}, "ghi": 796.44, "dhi": 116.34, "timestamp_local": "2020-03-13T14:00:00", "app_temp": 20, "azimuth": 195.77, "datetime": "2020-03-13:13", "temp": 21.2, "precip": 0, "clouds": 100, "ts": 1584104400}, {"rh": 22, "wind_spd": 2.87244, "timestamp_utc": "2020-03-13T14:00:00", "vis": 5, "slp": 1021, "pod": "d", "dni": 882.09, "elev_angle": 44.12, "pres": 893.6, "h_angle": 15, "dewpt": -2.3, "snow": 0, "uv": 2.3, "solar_rad": 179.675, "wind_dir": 210, "weather": {"icon": "c04d", "code": 804, "description": "Overcast clouds"}, "ghi": 718.7, "dhi": 111.71, "timestamp_local": "2020-03-13T15:00:00", "app_temp": 20.8, "azimuth": 216.33, "datetime": "2020-03-13:14", "temp": 22, "precip": 0, "clouds": 100, "ts": 1584108000}, {"rh": 21, "wind_spd": 2.09528, "timestamp_utc": "2020-03-13T15:00:00", "vis": 5, "slp": 1020, "pod": "d", "dni": 833.78, "elev_angle": 35.7, "pres": 893.1, "h_angle": 30, "dewpt": -2.8, "snow": 0, "uv": 2.2, "solar_rad": 253.505, "wind_dir": 210, "weather": {"icon": "c04d", "code": 804, "description": "Overcast clouds"}, "ghi": 582.58, "dhi": 102.69, "timestamp_local": "2020-03-13T16:00:00", "app_temp": 21.2, "azimuth": 232.57, "datetime": "2020-03-13:15", "temp": 22.3, "precip": 0.1, "clouds": 92, "ts": 1584111600}, {"rh": 21, "wind_spd": 1.69106, "timestamp_utc": "2020-03-13T16:00:00", "vis": 5, "slp": 1020, "pod": "d", "dni": 746.55, "elev_angle": 25.42, "pres": 893.5, "h_angle": 30, "dewpt": -0.5, "snow": 0, "uv": 4.6, "solar_rad": 402, "wind_dir": 200, "weather": {"icon": "c01d", "code": 800, "description": "Clear Sky"}, "ghi": 402, "dhi": 88.14, "timestamp_local": "2020-03-13T17:00:00", "app_temp": 21.1, "azimuth": 245.28, "datetime": "2020-03-13:16", "temp": 22.3, "precip": 0, "clouds": 1, "ts": 1584115200}, {"rh": 22, "wind_spd": 1.2924, "timestamp_utc": "2020-03-13T17:00:00", "vis": 0.5, "slp": 1020, "pod": "d", "dni": 580.02, "elev_angle": 14.12, "pres": 892.7, "h_angle": 60, "dewpt": -1.5, "snow": 0, "uv": 2.1, "solar_rad": 183.729, "wind_dir": 200, "weather": {"icon": "c03d", "code": 803, "description": "Broken clouds"}, "ghi": 198.84, "dhi": 65.13, "timestamp_local": "2020-03-13T18:00:00", "app_temp": 20.5, "azimuth": 255.76, "datetime": "2020-03-13:17", "temp": 21.7, "precip": 0.2, "clouds": 51, "ts": 1584118800}, {"rh": 31, "wind_spd": 4.68028, "timestamp_utc": "2020-03-13T18:00:00", "vis": 5, "slp": 1020, "pod": "n", "dni": 145.89, "elev_angle": 2.3, "pres": 892.7, "h_angle": 75, "dewpt": 0.7, "snow": 0, "uv": 0.8, "solar_rad": 4.5375, "wind_dir": 210, "weather": {"icon": "c04n", "code": 804, "description": "Overcast clouds"}, "ghi": 18.15, "dhi": 21.22, "timestamp_local": "2020-03-13T19:00:00", "app_temp": 18.7, "azimuth": 265.09, "datetime": "2020-03-13:18", "temp": 19.9, "precip": 0.2, "clouds": 100, "ts": 1584122400}, {"rh": 52, "wind_spd": 5.77189, "timestamp_utc": "2020-03-13T19:00:00", "vis": 5, "slp": 1020, "pod": "n", "dni": 0, "elev_angle": -9.69, "pres": 892.7, "h_angle": 75, "dewpt": -0.4, "snow": 0, "uv": 0, "solar_rad": 0, "wind_dir": 200, "weather": {"icon": "c04n", "code": 804, "description": "Overcast clouds"}, "ghi": 0, "dhi": 0, "timestamp_local": "2020-03-13T20:00:00", "app_temp": 17.9, "azimuth": 274.13, "datetime": "2020-03-13:19", "temp": 17.9, "precip": 0.1, "clouds": 100, "ts": 1584126000}, {"rh": 55, "wind_spd": 4.94474, "timestamp_utc": "2020-03-13T20:00:00", "vis": 5, "slp": 1020, "pod": "n", "dni": 0, "elev_angle": -21.53, "pres": 892.7, "h_angle": 90, "dewpt": -0.4, "snow": 0, "uv": 0, "solar_rad": 0, "wind_dir": 200, "weather": {"icon": "c04n", "code": 804, "description": "Overcast clouds"}, "ghi": 0, "dhi": 0, "timestamp_local": "2020-03-13T21:00:00", "app_temp": 16.3, "azimuth": 283.69, "datetime": "2020-03-13:20", "temp": 16.3, "precip": 0.1, "clouds": 100, "ts": 1584129600}, {"rh": 60, "wind_spd": 4.02337, "timestamp_utc": "2020-03-13T21:00:00", "vis": 1, "slp": 1020, "pod": "n", "dni": 0, "elev_angle": -32.85, "pres": 892.7, "h_angle": 90, "dewpt": -0.4, "snow": 0, "uv": 0, "solar_rad": 0, "wind_dir": 200, "weather": {"icon": "c02n", "code": 802, "description": "Scattered clouds"}, "ghi": 0, "dhi": 0, "timestamp_local": "2020-03-13T22:00:00", "app_temp": 14.7, "azimuth": 294.76, "datetime": "2020-03-13:21", "temp": 14.7, "precip": 0, "clouds": 26, "ts": 1584133200}, {"rh": 60, "wind_spd": 3.17522, "timestamp_utc": "2020-03-13T22:00:00", "vis": 5, "slp": 1020, "pod": "n", "dni": 0, "elev_angle": -43.06, "pres": 892.7, "h_angle": 90, "dewpt": -0.4, "snow": 0, "uv": 0, "solar_rad": 0, "wind_dir": 200, "weather": {"icon": "c04n", "code": 804, "description": "Overcast clouds"}, "ghi": 0, "dhi": 0, "timestamp_local": "2020-03-13T23:00:00", "app_temp": 13.6, "azimuth": 308.75, "datetime": "2020-03-13:22", "temp": 13.6, "precip": 0, "clouds": 100, "ts": 1584136800}, {"rh": 61, "wind_spd": 2.05488, "timestamp_utc": "2020-03-13T23:00:00", "vis": 1, "slp": 1020, "pod": "n", "dni": 0, "elev_angle": -51.1, "pres": 892.7, "h_angle": 90, "dewpt": -0.4, "snow": 0, "uv": 0, "solar_rad": 0, "wind_dir": 200, "weather": {"icon": "c02n", "code": 802, "description": "Scattered clouds"}, "ghi": 0, "dhi": 0, "timestamp_local": "2020-03-14T00:00:00", "app_temp": 12.9, "azimuth": 327.44, "datetime": "2020-03-13:23", "temp": 12.9, "precip": 0, "clouds": 29, "ts": 1584140400}], "sources": ["605400-99999", "imerg", "merra2", "era5", "modis"], "city_id": "2517748"}
{"timezone": "Europe/Madrid", "state_code": "55", "country_code": "ES", "lat": 40.723609, "lon": -5.204659, "city_name": "Cabezas del Villar", "station_id": "082020-99999", "data": [{"rh": 85, "wind_spd": 5.7, "timestamp_utc": "2020-03-13T00:00:00", "vis": 5, "slp": 1020, "pod": "n", "dni": 0, "elev_angle": -51.23, "pres": 926.8, "h_angle": -90, "dewpt": 7.3, "snow": 0, "uv": 0, "solar_rad": 0, "wind_dir": 70, "weather": {"icon": "c04n", "code": 804, "description": "Overcast clouds"}, "ghi": 0, "dhi": 0, "timestamp_local": "2020-03-13T01:00:00", "app_temp": 9.7, "azimuth": 347.38, "datetime": "2020-03-13:00", "temp": 9.7, "precip": 0, "clouds": 100, "ts": 1584057600}, {"rh": 86, "wind_spd": 4.1, "timestamp_utc": "2020-03-13T01:00:00", "vis": 5, "slp": 1020, "pod": "n", "dni": 0, "elev_angle": -51.33, "pres": 926.5, "h_angle": -90, "dewpt": 7.1, "snow": 0, "uv": 0, "solar_rad": 0, "wind_dir": 70, "weather": {"icon": "c04n", "code": 804, "description": "Overcast clouds"}, "ghi": 0, "dhi": 0, "timestamp_local": "2020-03-13T02:00:00", "app_temp": 9.2, "azimuth": 11.44, "datetime": "2020-03-13:01", "temp": 9.2, "precip": 0, "clouds": 100, "ts": 1584061200}, {"rh": 89, "wind_spd": 4.6, "timestamp_utc": "2020-03-13T02:00:00", "vis": 5, "slp": 1019, "pod": "n", "dni": 0, "elev_angle": -46.96, "pres": 925.6, "h_angle": -90, "dewpt": 6.8, "snow": 0, "uv": 0, "solar_rad": 0, "wind_dir": 70, "weather": {"icon": "c04n", "code": 804, "description": "Overcast clouds"}, "ghi": 0, "dhi": 0, "timestamp_local": "2020-03-13T03:00:00", "app_temp": 8.5, "azimuth": 33.46, "datetime": "2020-03-13:02", "temp": 8.5, "precip": 0, "clouds": 100, "ts": 1584064800}, {"rh": 88, "wind_spd": 2.6, "timestamp_utc": "2020-03-13T03:00:00", "vis": 5, "slp": 1019, "pod": "n", "dni": 0, "elev_angle": -39.3, "pres": 925.3, "h_angle": -90, "dewpt": 5.9, "snow": 0, "uv": 0, "solar_rad": 0, "wind_dir": 40, "weather": {"icon": "c04n", "code": 804, "description": "Overcast clouds"}, "ghi": 0, "dhi": 0, "timestamp_local": "2020-03-13T04:00:00", "app_temp": 7.6, "azimuth": 51.18, "datetime": "2020-03-13:03", "temp": 7.6, "precip": 0, "clouds": 100, "ts": 1584068400}, {"rh": 92, "wind_spd": 3.1, "timestamp_utc": "2020-03-13T04:00:00", "vis": 1.5, "slp": 1019, "pod": "n", "dni": 0, "elev_angle": -29.65, "pres": 924.9, "h_angle": -90, "dewpt": 6.1, "snow": 0, "uv": 0, "solar_rad": 0, "wind_dir": 40, "weather": {"icon": "c04n", "code": 804, "description": "Overcast clouds"}, "ghi": 0, "dhi": 0, "timestamp_local": "2020-03-13T05:00:00", "app_temp": 5.1, "azimuth": 65.15, "datetime": "2020-03-13:04", "temp": 7.2, "precip": 0, "clouds": 100, "ts": 1584072000}, {"rh": 92, "wind_spd": 4.02891, "timestamp_utc": "2020-03-13T05:00:00", "vis": 1.5, "slp": 1019, "pod": "n", "dni": 0, "elev_angle": -18.94, "pres": 924.9, "h_angle": -90, "dewpt": 5.9, "snow": 0, "uv": 0, "solar_rad": 0, "wind_dir": 40, "weather": {"icon": "c04n", "code": 804, "description": "Overcast clouds"}, "ghi": 0, "dhi": 0, "timestamp_local": "2020-03-13T06:00:00", "app_temp": 4.3, "azimuth": 76.68, "datetime": "2020-03-13:05", "temp": 7, "precip": 0, "clouds": 100, "ts": 1584075600}, {"rh": 93, "wind_spd": 3.6, "timestamp_utc": "2020-03-13T06:00:00", "vis": 1.5, "slp": 1019, "pod": "n", "dni": 0, "elev_angle": -7.73, "pres": 924.9, "h_angle": -90, "dewpt": 5.7, "snow": 0, "uv": 0, "solar_rad": 0, "wind_dir": 40, "weather": {"icon": "c04n", "code": 804, "description": "Overcast clouds"}, "ghi": 0, "dhi": 0, "timestamp_local": "2020-03-13T07:00:00", "app_temp": 4.2, "azimuth": 86.91, "datetime": "2020-03-13:06", "temp": 6.7, "precip": 0, "clouds": 100, "ts": 1584079200}, {"rh": 90, "wind_spd": 3.6, "timestamp_utc": "2020-03-13T07:00:00", "vis": 5, "slp": 1020, "pod": "n", "dni": 233.21, "elev_angle": 3.59, "pres": 925.8, "h_angle": -90, "dewpt": 5.6, "snow": 0, "uv": 0.8, "solar_rad": 6.3783, "wind_dir": 40, "weather": {"icon": "c04n", "code": 804, "description": "Overcast clouds"}, "ghi": 33.57, "dhi": 28.24, "timestamp_local": "2020-03-13T08:00:00", "app_temp": 4.5, "azimuth": 96.75, "datetime": "2020-03-13:07", "temp": 7, "precip": 0, "clouds": 100, "ts": 1584082800}, {"rh": 84, "wind_spd": 6.2, "timestamp_utc": "2020-03-13T08:00:00", "vis": 5, "slp": 1020, "pod": "d", "dni": 603.11, "elev_angle": 14.68, "pres": 925.8, "h_angle": -75, "dewpt": 5.9, "snow": 0, "uv": 1, "solar_rad": 40.109, "wind_dir": 60, "weather": {"icon": "c04d", "code": 804, "description": "Overcast clouds"}, "ghi": 211.1, "dhi": 65.64, "timestamp_local": "2020-03-13T09:00:00", "app_temp": 8.3, "azimuth": 106.98, "datetime": "2020-03-13:08", "temp": 8.3, "precip": 0, "clouds": 100, "ts": 1584086400}, {"rh": 82, "wind_spd": 4.51218, "timestamp_utc": "2020-03-13T09:00:00", "vis": 5, "slp": 1020, "pod": "d", "dni": 754.07, "elev_angle": 25.14, "pres": 926.2, "h_angle": -60, "dewpt": 6.2, "snow": 0, "uv": 1.4, "solar_rad": 76.0456, "wind_dir": 63, "weather": {"icon": "c04d", "code": 804, "description": "Overcast clouds"}, "ghi": 400.24, "dhi": 86.2, "timestamp_local": "2020-03-13T10:00:00", "app_temp": 8.9, "azimuth": 118.42, "datetime": "2020-03-13:09", "temp": 8.9, "precip": 0, "clouds": 100, "ts": 1584090000}, {"rh": 81, "wind_spd": 3.99266, "timestamp_utc": "2020-03-13T10:00:00", "vis": 5, "slp": 1021, "pod": "d", "dni": 834.4, "elev_angle": 34.41, "pres": 927.1, "h_angle": -45, "dewpt": 6.4, "snow": 0, "uv": 1.8, "solar_rad": 107.266, "wind_dir": 66, "weather": {"icon": "c04d", "code": 804, "description": "Overcast clouds"}, "ghi": 564.56, "dhi": 99.24, "timestamp_local": "2020-03-13T11:00:00", "app_temp": 9.4, "azimuth": 132.02, "datetime": "2020-03-13:10", "temp": 9.4, "precip": 0, "clouds": 100, "ts": 1584093600}, {"rh": 79, "wind_spd": 4.1, "timestamp_utc": "2020-03-13T11:00:00", "vis": 5, "slp": 1021, "pod": "d", "dni": 878.55, "elev_angle": 41.67, "pres": 927.4, "h_angle": -30, "dewpt": 6.7, "snow": 0, "uv": 2.2, "solar_rad": 171.197, "wind_dir": 70, "weather": {"icon": "c04d", "code": 804, "description": "Overcast clouds"}, "ghi": 684.79, "dhi": 107.21, "timestamp_local": "2020-03-13T12:00:00", "app_temp": 10, "azimuth": 148.72, "datetime": "2020-03-13:11", "temp": 10, "precip": 0, "clouds": 100, "ts": 1584097200}, {"rh": 74, "wind_spd": 3.95073, "timestamp_utc": "2020-03-13T12:00:00", "vis": 5, "slp": 1020, "pod": "d", "dni": 898.67, "elev_angle": 45.82, "pres": 926.5, "h_angle": -30, "dewpt": 7.5, "snow": 0, "uv": 3.6, "solar_rad": 527.887, "wind_dir": 56, "weather": {"icon": "c04d", "code": 804, "description": "Overcast clouds"}, "ghi": 748.78, "dhi": 111.06, "timestamp_local": "2020-03-13T13:00:00", "app_temp": 12, "azimuth": 168.72, "datetime": "2020-03-13:12", "temp": 12, "precip": 0, "clouds": 76, "ts": 1584100800}, {"rh": 68, "wind_spd": 4.5023, "timestamp_utc": "2020-03-13T13:00:00", "vis": 5, "slp": 1020, "pod": "d", "dni": 899.17, "elev_angle": 45.93, "pres": 927.1, "h_angle": -15, "dewpt": 8.4, "snow": 0, "uv": 3.5, "solar_rad": 497.925, "wind_dir": 43, "weather": {"icon": "c04d", "code": 804, "description": "Overcast clouds"}, "ghi": 750.46, "dhi": 111.15, "timestamp_local": "2020-03-13T14:00:00", "app_temp": 14.1, "azimuth": 190.32, "datetime": "2020-03-13:13", "temp": 14.1, "precip": 0, "clouds": 79, "ts": 1584104400}, {"rh": 63, "wind_spd": 3.6, "timestamp_utc": "2020-03-13T14:00:00", "vis": 5, "slp": 1019, "pod": "d", "dni": 880.15, "elev_angle": 41.98, "pres": 927.4, "h_angle": 0, "dewpt": 9.2, "snow": 0, "uv": 2.5, "solar_rad": 270.551, "wind_dir": 30, "weather": {"icon": "c04d", "code": 804, "description": "Overcast clouds"}, "ghi": 689.67, "dhi": 107.51, "timestamp_local": "2020-03-13T15:00:00", "app_temp": 16.1, "azimuth": 210.46, "datetime": "2020-03-13:14", "temp": 16.1, "precip": 0, "clouds": 94, "ts": 1584108000}, {"rh": 63, "wind_spd": 3.6, "timestamp_utc": "2020-03-13T15:00:00", "vis": 5, "slp": 1019, "pod": "d", "dni": 837.5, "elev_angle": 34.86, "pres": 927.7, "h_angle": 30, "dewpt": 9, "snow": 0, "uv": 1.9, "solar_rad": 143.053, "wind_dir": 20, "weather": {"icon": "c04d", "code": 804, "description": "Overcast clouds"}, "ghi": 572.21, "dhi": 99.78, "timestamp_local": "2020-03-13T16:00:00", "app_temp": 16, "azimuth": 227.35, "datetime": "2020-03-13:15", "temp": 16, "precip": 0, "clouds": 100, "ts": 1584111600}, {"rh": 61, "wind_spd": 3.6, "timestamp_utc": "2020-03-13T16:00:00", "vis": 5, "slp": 1018, "pod": "d", "dni": 759.7, "elev_angle": 25.67, "pres": 926.5, "h_angle": 45, "dewpt": 8.9, "snow": 0, "uv": 1.5, "solar_rad": 102.482, "wind_dir": 50, "weather": {"icon": "c04d", "code": 804, "description": "Overcast clouds"}, "ghi": 409.93, "dhi": 87.06, "timestamp_local": "2020-03-13T17:00:00", "app_temp": 16.3, "azimuth": 241.1, "datetime": "2020-03-13:16", "temp": 16.3, "precip": 0, "clouds": 100, "ts": 1584115200}, {"rh": 62, "wind_spd": 4.6, "timestamp_utc": "2020-03-13T17:00:00", "vis": 5, "slp": 1018, "pod": "d", "dni": 614.49, "elev_angle": 15.27, "pres": 926.5, "h_angle": 60, "dewpt": 8.6, "snow": 0, "uv": 1.1, "solar_rad": 55.4025, "wind_dir": 360, "weather": {"icon": "c04d", "code": 804, "description": "Overcast clouds"}, "ghi": 221.61, "dhi": 67.04, "timestamp_local": "2020-03-13T18:00:00", "app_temp": 15.7, "azimuth": 252.65, "datetime": "2020-03-13:17", "temp": 15.7, "precip": 0, "clouds": 100, "ts": 1584118800}, {"rh": 65, "wind_spd": 4.6, "timestamp_utc": "2020-03-13T18:00:00", "vis": 5, "slp": 1019, "pod": "n", "dni": 267.96, "elev_angle": 4.22, "pres": 927.1, "h_angle": 75, "dewpt": 7.6, "snow": 0, "uv": 1.2, "solar_rad": 28.8393, "wind_dir": 10, "weather": {"icon": "c04n", "code": 804, "description": "Overcast clouds"}, "ghi": 41.7, "dhi": 31.3, "timestamp_local": "2020-03-13T19:00:00", "app_temp": 14, "azimuth": 262.94, "datetime": "2020-03-13:18", "temp": 14, "precip": 0, "clouds": 77, "ts": 1584122400}, {"rh": 75, "wind_spd": 3.1, "timestamp_utc": "2020-03-13T19:00:00", "vis": 5, "slp": 1019, "pod": "n", "dni": 0, "elev_angle": -7.08, "pres": 926.8, "h_angle": 90, "dewpt": 7, "snow": 0, "uv": 0, "solar_rad": 0, "wind_dir": 20, "weather": {"icon": "c04n", "code": 804, "description": "Overcast clouds"}, "ghi": 0, "dhi": 0, "timestamp_local": "2020-03-13T20:00:00", "app_temp": 11.2, "azimuth": 272.8, "datetime": "2020-03-13:19", "temp": 11.2, "precip": 0, "clouds": 79, "ts": 1584126000}, {"rh": 83, "wind_spd": 4.1, "timestamp_utc": "2020-03-13T20:00:00", "vis": 1, "slp": 1020, "pod": "n", "dni": 0, "elev_angle": -18.28, "pres": 926.8, "h_angle": -90, "dewpt": 6.5, "snow": 0, "uv": 0, "solar_rad": 0, "wind_dir": 20, "weather": {"icon": "c02n", "code": 802, "description": "Scattered clouds"}, "ghi": 0, "dhi": 0, "timestamp_local": "2020-03-13T21:00:00", "app_temp": 9.2, "azimuth": 283.03, "datetime": "2020-03-13:20", "temp": 9.2, "precip": 0, "clouds": 32, "ts": 1584129600}, {"rh": 81, "wind_spd": 4.1, "timestamp_utc": "2020-03-13T21:00:00", "vis": 1, "slp": 1020, "pod": "n", "dni": 0, "elev_angle": -28.99, "pres": 926.5, "h_angle": -90, "dewpt": 6.2, "snow": 0, "uv": 0, "solar_rad": 0, "wind_dir": 40, "weather": {"icon": "c02n", "code": 802, "description": "Scattered clouds"}, "ghi": 0, "dhi": 0, "timestamp_local": "2020-03-13T22:00:00", "app_temp": 9.2, "azimuth": 294.51, "datetime": "2020-03-13:21", "temp": 9.2, "precip": 0, "clouds": 34, "ts": 1584133200}, {"rh": 81, "wind_spd": 3.1, "timestamp_utc": "2020-03-13T22:00:00", "vis": 5, "slp": 1021, "pod": "n", "dni": 0, "elev_angle": -38.64, "pres": 927.1, "h_angle": -90, "dewpt": 4.8, "snow": 0, "uv": 0, "solar_rad": 0, "wind_dir": 60, "weather": {"icon": "c01n", "code": 800, "description": "Clear Sky"}, "ghi": 0, "dhi": 0, "timestamp_local": "2020-03-13T23:00:00", "app_temp": 7.7, "azimuth": 308.35, "datetime": "2020-03-13:22", "temp": 7.7, "precip": 0, "clouds": 0, "ts": 1584136800}, {"rh": 85, "wind_spd": 1, "timestamp_utc": "2020-03-13T23:00:00", "vis": 5, "slp": 1022, "pod": "n", "dni": 0, "elev_angle": -46.36, "pres": 928, "h_angle": -90, "dewpt": 3.9, "snow": 0, "uv": 0, "solar_rad": 0, "wind_dir": 120, "weather": {"icon": "c01n", "code": 800, "description": "Clear Sky"}, "ghi": 0, "dhi": 0, "timestamp_local": "2020-03-14T00:00:00", "app_temp": 5.9, "azimuth": 325.86, "datetime": "2020-03-13:23", "temp": 6.1, "precip": 0, "clouds": 0, "ts": 1584140400}], "sources": ["082020-99999", "imerg", "merra2", "era5", "modis"], "city_id": "3127230"}
{"timezone": "Europe/Madrid", "state_code": "55", "country_code": "ES", "lat": 40.723609, "lon": -5.204659, "city_name": "Cabezas del Villar", "station_id": "082020-99999", "data": [{"rh": 85, "wind_spd": 5.7, "timestamp_utc": "2020-03-13T00:00:00", "vis": 5, "slp": 1020, "pod": "n", "dni": 0, "elev_angle": -51.23, "pres": 926.8, "h_angle": -90, "dewpt": 7.3, "snow": 0, "uv": 0, "solar_rad": 0, "wind_dir": 70, "weather": {"icon": "c04n", "code": 804, "description": "Overcast clouds"}, "ghi": 0, "dhi": 0, "timestamp_local": "2020-03-13T01:00:00", "app_temp": 9.7, "azimuth": 347.38, "datetime": "2020-03-13:00", "temp": 9.7, "precip": 0, "clouds": 100, "ts": 1584057600}, {"rh": 86, "wind_spd": 4.1, "timestamp_utc": "2020-03-13T01:00:00", "vis": 5, "slp": 1020, "pod": "n", "dni": 0, "elev_angle": -51.33, "pres": 926.5, "h_angle": -90, "dewpt": 7.1, "snow": 0, "uv": 0, "solar_rad": 0, "wind_dir": 70, "weather": {"icon": "c04n", "code": 804, "description": "Overcast clouds"}, "ghi": 0, "dhi": 0, "timestamp_local": "2020-03-13T02:00:00", "app_temp": 9.2, "azimuth": 11.44, "datetime": "2020-03-13:01", "temp": 9.2, "precip": 0, "clouds": 100, "ts": 1584061200}, {"rh": 89, "wind_spd": 4.6, "timestamp_utc": "2020-03-13T02:00:00", "vis": 5, "slp": 1019, "pod": "n", "dni": 0, "elev_angle": -46.96, "pres": 925.6, "h_angle": -90, "dewpt": 6.8, "snow": 0, "uv": 0, "solar_rad": 0, "wind_dir": 70, "weather": {"icon": "c04n", "code": 804, "description": "Overcast clouds"}, "ghi": 0, "dhi": 0, "timestamp_local": "2020-03-13T03:00:00", "app_temp": 8.5, "azimuth": 33.46, "datetime": "2020-03-13:02", "temp": 8.5, "precip": 0, "clouds": 100, "ts": 1584064800}, {"rh": 88, "wind_spd": 2.6, "timestamp_utc": "2020-03-13T03:00:00", "vis": 5, "slp": 1019, "pod": "n", "dni": 0, "elev_angle": -39.3, "pres": 925.3, "h_angle": -90, "dewpt": 5.9, "snow": 0, "uv": 0, "solar_rad": 0, "wind_dir": 40, "weather": {"icon": "c04n", "code": 804, "description": "Overcast clouds"}, "ghi": 0, "dhi": 0, "timestamp_local": "2020-03-13T04:00:00", "app_temp": 7.6, "azimuth": 51.18, "datetime": "2020-03-13:03", "temp": 7.6, "precip": 0, "clouds": 100, "ts": 1584068400}, {"rh": 92, "wind_spd": 3.1, "timestamp_utc": "2020-03-13T04:00:00", "vis": 1.5, "slp": 1019, "pod": "n", "dni": 0, "elev_angle": -29.65, "pres": 924.9, "h_angle": -90, "dewpt": 6.1, "snow": 0, "uv": 0, "solar_rad": 0, "wind_dir": 40, "weather": {"icon": "c04n", "code": 804, "description": "Overcast clouds"}, "ghi": 0, "dhi": 0, "timestamp_local": "2020-03-13T05:00:00", "app_temp": 5.1, "azimuth": 65.15, "datetime": "2020-03-13:04", "temp": 7.2, "precip": 0, "clouds": 100, "ts": 1584072000}, {"rh": 92, "wind_spd": 4.02891, "timestamp_utc": "2020-03-13T05:00:00", "vis": 1.5, "slp": 1019, "pod": "n", "dni": 0, "elev_angle": -18.94, "pres": 924.9, "h_angle": -90, "dewpt": 5.9, "snow": 0, "uv": 0, "solar_rad": 0, "wind_dir": 40, "weather": {"icon": "c04n", "code": 804, "description": "Overcast clouds"}, "ghi": 0, "dhi": 0, "timestamp_local": "2020-03-13T06:00:00", "app_temp": 4.3, "azimuth": 76.68, "datetime": "2020-03-13:05", "temp": 7, "precip": 0, "clouds": 100, "ts": 1584075600}, {"rh": 93, "wind_spd": 3.6, "timestamp_utc": "2020-03-13T06:00:00", "vis": 1.5, "slp": 1019, "pod": "n", "dni": 0, "elev_angle": -7.73, "pres": 924.9, "h_angle": -90, "dewpt": 5.7, "snow": 0, "uv": 0, "solar_rad": 0, "wind_dir": 40, "weather": {"icon": "c04n", "code": 804, "description": "Overcast clouds"}, "ghi": 0, "dhi": 0, "timestamp_local": "2020-03-13T07:00:00", "app_temp": 4.2, "azimuth": 86.91, "datetime": "2020-03-13:06", "temp": 6.7, "precip": 0, "clouds": 100, "ts": 1584079200}, {"rh": 90, "wind_spd": 3.6, "timestamp_utc": "2020-03-13T07:00:00", "vis": 5, "slp": 1020, "pod": "n", "dni": 233.21, "elev_angle": 3.59, "pres": 925.8, "h_angle": -90, "dewpt": 5.6, "snow": 0, "uv": 0.8, "solar_rad": 6.3783, "wind_dir": 40, "weather": {"icon": "c04n", "code": 804, "description": "Overcast clouds"}, "ghi": 33.57, "dhi": 28.24, "timestamp_local": "2020-03-13T08:00:00", "app_temp": 4.5, "azimuth": 96.75, "datetime": "2020-03-13:07", "temp": 7, "precip": 0, "clouds": 100, "ts": 1584082800}, {"rh": 84, "wind_spd": 6.2, "timestamp_utc": "2020-03-13T08:00:00", "vis": 5, "slp": 1020, "pod": "d", "dni": 603.11, "elev_angle": 14.68, "pres": 925.8, "h_angle": -75, "dewpt": 5.9, "snow": 0, "uv": 1, "solar_rad": 40.109, "wind_dir": 60, "weather": {"icon": "c04d", "code": 804, "description": "Overcast clouds"}, "ghi": 211.1, "dhi": 65.64, "timestamp_local": "2020-03-13T09:00:00", "app_temp": 8.3, "azimuth": 106.98, "datetime": "2020-03-13:08", "temp": 8.3, "precip": 0, "clouds": 100, "ts": 1584086400}, {"rh": 82, "wind_spd": 4.51218, "timestamp_utc": "2020-03-13T09:00:00", "vis": 5, "slp": 1020, "pod": "d", "dni": 754.07, "elev_angle": 25.14, "pres": 926.2, "h_angle": -60, "dewpt": 6.2, "snow": 0, "uv": 1.4, "solar_rad": 76.0456, "wind_dir": 63, "weather": {"icon": "c04d", "code": 804, "description": "Overcast clouds"}, "ghi": 400.24, "dhi": 86.2, "timestamp_local": "2020-03-13T10:00:00", "app_temp": 8.9, "azimuth": 118.42, "datetime": "2020-03-13:09", "temp": 8.9, "precip": 0, "clouds": 100, "ts": 1584090000}, {"rh": 81, "wind_spd": 3.99266, "timestamp_utc": "2020-03-13T10:00:00", "vis": 5, "slp": 1021, "pod": "d", "dni": 834.4, "elev_angle": 34.41, "pres": 927.1, "h_angle": -45, "dewpt": 6.4, "snow": 0, "uv": 1.8, "solar_rad": 107.266, "wind_dir": 66, "weather": {"icon": "c04d", "code": 804, "description": "Overcast clouds"}, "ghi": 564.56, "dhi": 99.24, "timestamp_local": "2020-03-13T11:00:00", "app_temp": 9.4, "azimuth": 132.02, "datetime": "2020-03-13:10", "temp": 9.4, "precip": 0, "clouds": 100, "ts": 1584093600}, {"rh": 79, "wind_spd": 4.1, "timestamp_utc": "2020-03-13T11:00:00", "vis": 5, "slp": 1021, "pod": "d", "dni": 878.55, "elev_angle": 41.67, "pres": 927.4, "h_angle": -30, "dewpt": 6.7, "snow": 0, "uv": 2.2, "solar_rad": 171.197, "wind_dir": 70, "weather": {"icon": "c04d", "code": 804, "description": "Overcast clouds"}, "ghi": 684.79, "dhi": 107.21, "timestamp_local": "2020-03-13T12:00:00", "app_temp": 10, "azimuth": 148.72, "datetime": "2020-03-13:11", "temp": 10, "precip": 0, "clouds": 100, "ts": 1584097200}, {"rh": 74, "wind_spd": 3.95073, "timestamp_utc": "2020-03-13T12:00:00", "vis": 5, "slp": 1020, "pod": "d", "dni": 898.67, "elev_angle": 45.82, "pres": 926.5, "h_angle": -30, "dewpt": 7.5, "snow": 0, "uv": 3.6, "solar_rad": 527.887, "wind_dir": 56, "weather": {"icon": "c04d", "code": 804, "description": "Overcast clouds"}, "ghi": 748.78, "dhi": 111.06, "timestamp_local": "2020-03-13T13:00:00", "app_temp": 12, "azimuth": 168.72, "datetime": "2020-03-13:12", "temp": 12, "precip": 0, "clouds": 76, "ts": 1584100800}, {"rh": 68, "wind_spd": 4.5023, "timestamp_utc": "2020-03-13T13:00:00", "vis": 5, "slp": 1020, "pod": "d", "dni": 899.17, "elev_angle": 45.93, "pres": 927.1, "h_angle": -15, "dewpt": 8.4, "snow": 0, "uv": 3.5, "solar_rad": 497.925, "wind_dir": 43, "weather": {"icon": "c04d", "code": 804, "description": "Overcast clouds"}, "ghi": 750.46, "dhi": 111.15, "timestamp_local": "2020-03-13T14:00:00", "app_temp": 14.1, "azimuth": 190.32, "datetime": "2020-03-13:13", "temp": 14.1, "precip": 0, "clouds": 79, "ts": 1584104400}, {"rh": 63, "wind_spd": 3.6, "timestamp_utc": "2020-03-13T14:00:00", "vis": 5, "slp": 1019, "pod": "d", "dni": 880.15, "elev_angle": 41.98, "pres": 927.4, "h_angle": 0, "dewpt": 9.2, "snow": 0, "uv": 2.5, "solar_rad": 270.551, "wind_dir": 30, "weather": {"icon": "c04d", "code": 804, "description": "Overcast clouds"}, "ghi": 689.67, "dhi": 107.51, "timestamp_local": "2020-03-13T15:00:00", "app_temp": 16.1, "azimuth": 210.46, "datetime": "2020-03-13:14", "temp": 16.1, "precip": 0, "clouds": 94, "ts": 1584108000}, {"rh": 63, "wind_spd": 3.6, "timestamp_utc": "2020-03-13T15:00:00", "vis": 5, "slp": 1019, "pod": "d", "dni": 837.5, "elev_angle": 34.86, "pres": 927.7, "h_angle": 30, "dewpt": 9, "snow": 0, "uv": 1.9, "solar_rad": 143.053, "wind_dir": 20, "weather": {"icon": "c04d", "code": 804, "description": "Overcast clouds"}, "ghi": 572.21, "dhi": 99.78, "timestamp_local": "2020-03-13T16:00:00", "app_temp": 16, "azimuth": 227.35, "datetime": "2020-03-13:15", "temp": 16, "precip": 0, "clouds": 100, "ts": 1584111600}, {"rh": 61, "wind_spd": 3.6, "timestamp_utc": "2020-03-13T16:00:00", "vis": 5, "slp": 1018, "pod": "d", "dni": 759.7, "elev_angle": 25.67, "pres": 926.5, "h_angle": 45, "dewpt": 8.9, "snow": 0, "uv": 1.5, "solar_rad": 102.482, "wind_dir": 50, "weather": {"icon": "c04d", "code": 804, "description": "Overcast clouds"}, "ghi": 409.93, "dhi": 87.06, "timestamp_local": "2020-03-13T17:00:00", "app_temp": 16.3, "azimuth": 241.1, "datetime": "2020-03-13:16", "temp": 16.3, "precip": 0, "clouds": 100, "ts": 1584115200}, {"rh": 62, "wind_spd": 4.6, "timestamp_utc": "2020-03-13T17:00:00", "vis": 5, "slp": 1018, "pod": "d", "dni": 614.49, "elev_angle": 15.27, "pres": 926.5, "h_angle": 60, "dewpt": 8.6, "snow": 0, "uv": 1.1, "solar_rad": 55.4025, "wind_dir": 360, "weather": {"icon": "c04d", "code": 804, "description": "Overcast clouds"}, "ghi": 221.61, "dhi": 67.04, "timestamp_local": "2020-03-13T18:00:00", "app_temp": 15.7, "azimuth": 252.65, "datetime": "2020-03-13:17", "temp": 15.7, "precip": 0, "clouds": 100, "ts": 1584118800}, {"rh": 65, "wind_spd": 4.6, "timestamp_utc": "2020-03-13T18:00:00", "vis": 5, "slp": 1019, "pod": "n", "dni": 267.96, "elev_angle": 4.22, "pres": 927.1, "h_angle": 75, "dewpt": 7.6, "snow": 0, "uv": 1.2, "solar_rad": 28.8393, "wind_dir": 10, "weather": {"icon": "c04n", "code": 804, "description": "Overcast clouds"}, "ghi": 41.7, "dhi": 31.3, "timestamp_local": "2020-03-13T19:00:00", "app_temp": 14, "azimuth": 262.94, "datetime": "2020-03-13:18", "temp": 14, "precip": 0, "clouds": 77, "ts": 1584122400}, {"rh": 75, "wind_spd": 3.1, "timestamp_utc": "2020-03-13T19:00:00", "vis": 5, "slp": 1019, "pod": "n", "dni": 0, "elev_angle": -7.08, "pres": 926.8, "h_angle": 90, "dewpt": 7, "snow": 0, "uv": 0, "solar_rad": 0, "wind_dir": 20, "weather": {"icon": "c04n", "code": 804, "description": "Overcast clouds"}, "ghi": 0, "dhi": 0, "timestamp_local": "2020-03-13T20:00:00", "app_temp": 11.2, "azimuth": 272.8, "datetime": "2020-03-13:19", "temp": 11.2, "precip": 0, "clouds": 79, "ts": 1584126000}, {"rh": 83, "wind_spd": 4.1, "timestamp_utc": "2020-03-13T20:00:00", "vis": 1, "slp": 1020, "pod": "n", "dni": 0, "elev_angle": -18.28, "pres": 926.8, "h_angle": -90, "dewpt": 6.5, "snow": 0, "uv": 0, "solar_rad": 0, "wind_dir": 20, "weather": {"icon": "c02n", "code": 802, "description": "Scattered clouds"}, "ghi": 0, "dhi": 0, "timestamp_local": "2020-03-13T21:00:00", "app_temp": 9.2, "azimuth": 283.03, "datetime": "2020-03-13:20", "temp": 9.2, "precip": 0, "clouds": 32, "ts": 1584129600}, {"rh": 81, "wind_spd": 4.1, "timestamp_utc": "2020-03-13T21:00:00", "vis": 1, "slp": 1020, "pod": "n", "dni": 0, "elev_angle": -28.99, "pres": 926.5, "h_angle": -90, "dewpt": 6.2, "snow": 0, "uv": 0, "solar_rad": 0, "wind_dir": 40, "weather": {"icon": "c02n", "code": 802, "description": "Scattered clouds"}, "ghi": 0, "dhi": 0, "timestamp_local": "2020-03-13T22:00:00", "app_temp": 9.2, "azimuth": 294.51, "datetime": "2020-03-13:21", "temp": 9.2, "precip": 0, "clouds": 34, "ts": 1584133200}, {"rh": 81, "wind_spd": 3.1, "timestamp_utc": "2020-03-13T22:00:00", "vis": 5, "slp": 1021, "pod": "n", "dni": 0, "elev_angle": -38.64, "pres": 927.1, "h_angle": -90, "dewpt": 4.8, "snow": 0, "uv": 0, "solar_rad": 0, "wind_dir": 60, "weather": {"icon": "c01n", "code": 800, "description": "Clear Sky"}, "ghi": 0, "dhi": 0, "timestamp_local": "2020-03-13T23:00:00", "app_temp": 7.7, "azimuth": 308.35, "datetime": "2020-03-13:22", "temp": 7.7, "precip": 0, "clouds": 0, "ts": 1584136800}, {"rh": 85, "wind_spd": 1, "timestamp_utc": "2020-03-13T23:00:00", "vis": 5, "slp": 1022, "pod": "n", "dni": 0, "elev_angle": -46.36, "pres": 928, "h_angle": -90, "dewpt": 3.9, "snow": 0, "uv": 0, "solar_rad": 0, "wind_dir": 120, "weather": {"icon": "c01n", "code": 800, "description": "Clear Sky"}, "ghi": 0, "dhi": 0, "timestamp_local": "2020-03-14T00:00:00", "app_temp": 5.9, "azimuth": 325.86, "datetime": "2020-03-13:23", "temp": 6.1, "precip": 0, "clouds": 0, "ts": 1584140400}], "sources": ["082020-99999", "imerg", "merra2", "era5", "modis"], "city_id": "3127230"}
{"timezone": "Europe/Madrid", "state_code": "56", "country_code": "ES", "lat": 42.210419, "lon": 1.240819, "city_name": "Coll de Narg\u00f3", "station_id": "081170-99999", "data": [{"rh": 81, "wind_spd": 0.763138, "timestamp_utc": "2020-03-13T00:00:00", "vis": 5, "slp": 1016.3, "pod": "n", "dni": 0, "elev_angle": -50.62, "pres": 914.8, "h_angle": -90, "dewpt": 6.2, "snow": 0, "uv": 0, "solar_rad": 0, "wind_dir": 45, "weather": {"icon": "r01n", "code": 500, "description": "Light rain"}, "ghi": 0, "dhi": 0, "timestamp_local": "2020-03-13T01:00:00", "app_temp": 8.4, "azimuth": 357.63, "datetime": "2020-03-13:00", "temp": 8.4, "precip": 0.6, "clouds": 100, "ts": 1584057600}, {"rh": 77, "wind_spd": 0.842589, "timestamp_utc": "2020-03-13T01:00:00", "vis": 5, "slp": 1016.4, "pod": "n", "dni": 0, "elev_angle": -48.81, "pres": 914.9, "h_angle": -90, "dewpt": 6.5, "snow": 0, "uv": 0, "solar_rad": 0, "wind_dir": 180, "weather": {"icon": "c04n", "code": 804, "description": "Overcast clouds"}, "ghi": 0, "dhi": 0, "timestamp_local": "2020-03-13T02:00:00", "app_temp": 8.2, "azimuth": 20.73, "datetime": "2020-03-13:01", "temp": 8.2, "precip": 0.4, "clouds": 100, "ts": 1584061200}, {"rh": 80, "wind_spd": 1.08108, "timestamp_utc": "2020-03-13T02:00:00", "vis": 5, "slp": 1015.5, "pod": "n", "dni": 0, "elev_angle": -43.09, "pres": 914.1, "h_angle": -90, "dewpt": 7.1, "snow": 0, "uv": 0, "solar_rad": 0, "wind_dir": 22, "weather": {"icon": "c04n", "code": 804, "description": "Overcast clouds"}, "ghi": 0, "dhi": 0, "timestamp_local": "2020-03-13T03:00:00", "app_temp": 7.6, "azimuth": 40.74, "datetime": "2020-03-13:02", "temp": 7.6, "precip": 0.2, "clouds": 100, "ts": 1584064800}, {"rh": 85, "wind_spd": 0.776533, "timestamp_utc": "2020-03-13T03:00:00", "vis": 5, "slp": 1015.4, "pod": "n", "dni": 0, "elev_angle": -34.71, "pres": 914.2, "h_angle": -90, "dewpt": 7.2, "snow": 0, "uv": 0, "solar_rad": 0, "wind_dir": 135, "weather": {"icon": "c04n", "code": 804, "description": "Overcast clouds"}, "ghi": 0, "dhi": 0, "timestamp_local": "2020-03-13T04:00:00", "app_temp": 7.4, "azimuth": 56.76, "datetime": "2020-03-13:03", "temp": 7, "precip": 0, "clouds": 100, "ts": 1584068400}, {"rh": 89, "wind_spd": 0.683894, "timestamp_utc": "2020-03-13T04:00:00", "vis": 5, "slp": 1015.1, "pod": "n", "dni": 0, "elev_angle": -24.78, "pres": 913.9, "h_angle": -90, "dewpt": 6.8, "snow": 0, "uv": 0, "solar_rad": 0, "wind_dir": 247, "weather": {"icon": "c04n", "code": 804, "description": "Overcast clouds"}, "ghi": 0, "dhi": 0, "timestamp_local": "2020-03-13T05:00:00", "app_temp": 7.5, "azimuth": 69.72, "datetime": "2020-03-13:04", "temp": 6.9, "precip": 0, "clouds": 100, "ts": 1584072000}, {"rh": 91, "wind_spd": 0.819818, "timestamp_utc": "2020-03-13T05:00:00", "vis": 1.5, "slp": 1015.5, "pod": "n", "dni": 0, "elev_angle": -14.03, "pres": 913.9, "h_angle": -90, "dewpt": 6.5, "snow": 0, "uv": 0, "solar_rad": 0, "wind_dir": 202, "weather": {"icon": "c04n", "code": 804, "description": "Overcast clouds"}, "ghi": 0, "dhi": 0, "timestamp_local": "2020-03-13T06:00:00", "app_temp": 7.3, "azimuth": 80.82, "datetime": "2020-03-13:05", "temp": 7.3, "precip": 0, "clouds": 100, "ts": 1584075600}, {"rh": 95, "wind_spd": 0.830531, "timestamp_utc": "2020-03-13T06:00:00", "vis": 1.5, "slp": 1015.9, "pod": "n", "dni": 0, "elev_angle": -2.95, "pres": 914.1, "h_angle": -90, "dewpt": 6.1, "snow": 0, "uv": 0, "solar_rad": 0, "wind_dir": 0, "weather": {"icon": "c04n", "code": 804, "description": "Overcast clouds"}, "ghi": 0, "dhi": 0, "timestamp_local": "2020-03-13T07:00:00", "app_temp": 7.1, "azimuth": 91.03, "datetime": "2020-03-13:06", "temp": 6.9, "precip": 0, "clouds": 100, "ts": 1584079200}, {"rh": 97, "wind_spd": 1.47699, "timestamp_utc": "2020-03-13T07:00:00", "vis": 1.5, "slp": 1016.3, "pod": "d", "dni": 431.5, "elev_angle": 8.1, "pres": 914, "h_angle": -90, "dewpt": 5.7, "snow": 0, "uv": 0.9, "solar_rad": 9.898, "wind_dir": 45, "weather": {"icon": "c04d", "code": 804, "description": "Overcast clouds"}, "ghi": 98.98, "dhi": 46.93, "timestamp_local": "2020-03-13T08:00:00", "app_temp": 5.9, "azimuth": 101.18, "datetime": "2020-03-13:07", "temp": 6.7, "precip": 0, "clouds": 100, "ts": 1584082800}, {"rh": 96, "wind_spd": 1.07032, "timestamp_utc": "2020-03-13T08:00:00", "vis": 1.5, "slp": 1016.5, "pod": "d", "dni": 671.3, "elev_angle": 18.75, "pres": 914.6, "h_angle": -75, "dewpt": 7, "snow": 0, "uv": 1.2, "solar_rad": 28.381, "wind_dir": 90, "weather": {"icon": "c04d", "code": 804, "description": "Overcast clouds"}, "ghi": 283.81, "dhi": 74.81, "timestamp_local": "2020-03-13T09:00:00", "app_temp": 7.3, "azimuth": 112.04, "datetime": "2020-03-13:08", "temp": 7.3, "precip": 0, "clouds": 100, "ts": 1584086400}, {"rh": 94, "wind_spd": 1.93459, "timestamp_utc": "2020-03-13T09:00:00", "vis": 1.5, "slp": 1016.9, "pod": "d", "dni": 785.97, "elev_angle": 28.55, "pres": 915.3, "h_angle": -60, "dewpt": 7.1, "snow": 0, "uv": 1.6, "solar_rad": 46.115, "wind_dir": 202, "weather": {"icon": "c04d", "code": 804, "description": "Overcast clouds"}, "ghi": 461.15, "dhi": 91.71, "timestamp_local": "2020-03-13T10:00:00", "app_temp": 7.9, "azimuth": 124.45, "datetime": "2020-03-13:09", "temp": 7.9, "precip": 0, "clouds": 100, "ts": 1584090000}, {"rh": 93, "wind_spd": 2.30197, "timestamp_utc": "2020-03-13T10:00:00", "vis": 1.5, "slp": 1016.8, "pod": "d", "dni": 849.15, "elev_angle": 36.85, "pres": 915.6, "h_angle": -45, "dewpt": 6.7, "snow": 0, "uv": 1.9, "solar_rad": 60.533, "wind_dir": 225, "weather": {"icon": "c04d", "code": 804, "description": "Overcast clouds"}, "ghi": 605.33, "dhi": 102.43, "timestamp_local": "2020-03-13T11:00:00", "app_temp": 8.1, "azimuth": 139.32, "datetime": "2020-03-13:10", "temp": 8.1, "precip": 0, "clouds": 100, "ts": 1584093600}, {"rh": 90, "wind_spd": 2.97717, "timestamp_utc": "2020-03-13T11:00:00", "vis": 5, "slp": 1016.6, "pod": "d", "dni": 882.5, "elev_angle": 42.72, "pres": 916, "h_angle": -30, "dewpt": 6.6, "snow": 0, "uv": 2.2, "solar_rad": 133.125, "wind_dir": 247, "weather": {"icon": "c04d", "code": 804, "description": "Overcast clouds"}, "ghi": 700.66, "dhi": 108.58, "timestamp_local": "2020-03-13T12:00:00", "app_temp": 8.5, "azimuth": 157.32, "datetime": "2020-03-13:11", "temp": 8.5, "precip": 0, "clouds": 100, "ts": 1584097200}, {"rh": 85, "wind_spd": 3.01088, "timestamp_utc": "2020-03-13T12:00:00", "vis": 5, "slp": 1015.9, "pod": "d", "dni": 894.14, "elev_angle": 45.14, "pres": 916.1, "h_angle": -15, "dewpt": 6.5, "snow": 0, "uv": 2.3, "solar_rad": 140.178, "wind_dir": 202, "weather": {"icon": "c04d", "code": 804, "description": "Overcast clouds"}, "ghi": 737.78, "dhi": 110.81, "timestamp_local": "2020-03-13T13:00:00", "app_temp": 9.6, "azimuth": 177.92, "datetime": "2020-03-13:12", "temp": 9.6, "precip": 0, "clouds": 100, "ts": 1584100800}, {"rh": 84, "wind_spd": 2.94754, "timestamp_utc": "2020-03-13T13:00:00", "vis": 5, "slp": 1015.1, "pod": "d", "dni": 886.5, "elev_angle": 43.53, "pres": 915.6, "h_angle": -15, "dewpt": 6.2, "snow": 0, "uv": 2.3, "solar_rad": 135.502, "wind_dir": 225, "weather": {"icon": "c04d", "code": 804, "description": "Overcast clouds"}, "ghi": 713.17, "dhi": 109.34, "timestamp_local": "2020-03-13T14:00:00", "app_temp": 9.9, "azimuth": 198.81, "datetime": "2020-03-13:13", "temp": 9.9, "precip": 0, "clouds": 100, "ts": 1584104400}, {"rh": 83, "wind_spd": 2.54053, "timestamp_utc": "2020-03-13T14:00:00", "vis": 5, "slp": 1013.9, "pod": "d", "dni": 858.01, "elev_angle": 38.28, "pres": 914.8, "h_angle": 15, "dewpt": 5.8, "snow": 0, "uv": 2.4, "solar_rad": 245.35, "wind_dir": 225, "weather": {"icon": "c04d", "code": 804, "description": "Overcast clouds"}, "ghi": 629.18, "dhi": 104.02, "timestamp_local": "2020-03-13T15:00:00", "app_temp": 10.2, "azimuth": 217.44, "datetime": "2020-03-13:14", "temp": 10.2, "precip": 0, "clouds": 92, "ts": 1584108000}, {"rh": 86, "wind_spd": 2.48461, "timestamp_utc": "2020-03-13T15:00:00", "vis": 5, "slp": 1013.7, "pod": "d", "dni": 802.06, "elev_angle": 30.4, "pres": 914.8, "h_angle": 30, "dewpt": 6.1, "snow": 0, "uv": 1.9, "solar_rad": 181.35, "wind_dir": 270, "weather": {"icon": "c04d", "code": 804, "description": "Overcast clouds"}, "ghi": 493.99, "dhi": 94.33, "timestamp_local": "2020-03-13T16:00:00", "app_temp": 9.7, "azimuth": 232.92, "datetime": "2020-03-13:15", "temp": 9.7, "precip": 0, "clouds": 93, "ts": 1584111600}, {"rh": 91, "wind_spd": 2.22629, "timestamp_utc": "2020-03-13T16:00:00", "vis": 1.5, "slp": 1013.6, "pod": "d", "dni": 701.14, "elev_angle": 20.85, "pres": 914.2, "h_angle": 30, "dewpt": 6.6, "snow": 0, "uv": 1.3, "solar_rad": 32.192, "wind_dir": 270, "weather": {"icon": "c04d", "code": 804, "description": "Overcast clouds"}, "ghi": 321.92, "dhi": 78.93, "timestamp_local": "2020-03-13T17:00:00", "app_temp": 8.7, "azimuth": 245.77, "datetime": "2020-03-13:16", "temp": 8.7, "precip": 0, "clouds": 100, "ts": 1584115200}, {"rh": 95, "wind_spd": 1.886, "timestamp_utc": "2020-03-13T17:00:00", "vis": 1.5, "slp": 1013.3, "pod": "d", "dni": 500.35, "elev_angle": 10.35, "pres": 913.8, "h_angle": 60, "dewpt": 6.5, "snow": 0, "uv": 1, "solar_rad": 25.5926, "wind_dir": 45, "weather": {"icon": "c04d", "code": 804, "description": "Overcast clouds"}, "ghi": 135.74, "dhi": 54.14, "timestamp_local": "2020-03-13T18:00:00", "app_temp": 7.8, "azimuth": 256.89, "datetime": "2020-03-13:17", "temp": 7.8, "precip": 0, "clouds": 97, "ts": 1584118800}, {"rh": 100, "wind_spd": 1.52689, "timestamp_utc": "2020-03-13T18:00:00", "vis": 1.5, "slp": 1014, "pod": "n", "dni": 0, "elev_angle": -0.63, "pres": 913.8, "h_angle": 75, "dewpt": 6.1, "snow": 0, "uv": 0, "solar_rad": 0, "wind_dir": 202, "weather": {"icon": "c04n", "code": 804, "description": "Overcast clouds"}, "ghi": 0, "dhi": 0, "timestamp_local": "2020-03-13T19:00:00", "app_temp": 6.2, "azimuth": 267.14, "datetime": "2020-03-13:18", "temp": 7, "precip": 0, "clouds": 97, "ts": 1584122400}, {"rh": 100, "wind_spd": 1.21411, "timestamp_utc": "2020-03-13T19:00:00", "vis": 1.5, "slp": 1014.3, "pod": "n", "dni": 0, "elev_angle": -11.72, "pres": 913.9, "h_angle": 75, "dewpt": 6.3, "snow": 0, "uv": 0, "solar_rad": 0, "wind_dir": 202, "weather": {"icon": "c04n", "code": 804, "description": "Overcast clouds"}, "ghi": 0, "dhi": 0, "timestamp_local": "2020-03-13T20:00:00", "app_temp": 6.2, "azimuth": 277.31, "datetime": "2020-03-13:19", "temp": 6.7, "precip": 0, "clouds": 99, "ts": 1584126000}, {"rh": 100, "wind_spd": 1.37613, "timestamp_utc": "2020-03-13T20:00:00", "vis": 1.5, "slp": 1014.3, "pod": "n", "dni": 0, "elev_angle": -22.53, "pres": 913.7, "h_angle": -90, "dewpt": 6.2, "snow": 0, "uv": 0, "solar_rad": 0, "wind_dir": 202, "weather": {"icon": "c04n", "code": 804, "description": "Overcast clouds"}, "ghi": 0, "dhi": 0, "timestamp_local": "2020-03-13T21:00:00", "app_temp": 5.9, "azimuth": 288.19, "datetime": "2020-03-13:20", "temp": 6.6, "precip": 0, "clouds": 98, "ts": 1584129600}, {"rh": 100, "wind_spd": 1.34428, "timestamp_utc": "2020-03-13T21:00:00", "vis": 1.5, "slp": 1014.3, "pod": "n", "dni": 0, "elev_angle": -32.63, "pres": 913.6, "h_angle": -90, "dewpt": 6.3, "snow": 0, "uv": 0, "solar_rad": 0, "wind_dir": 0, "weather": {"icon": "c04n", "code": 804, "description": "Overcast clouds"}, "ghi": 0, "dhi": 0, "timestamp_local": "2020-03-13T22:00:00", "app_temp": 5.7, "azimuth": 300.72, "datetime": "2020-03-13:21", "temp": 6.3, "precip": 0, "clouds": 100, "ts": 1584133200}, {"rh": 100, "wind_spd": 1.25696, "timestamp_utc": "2020-03-13T22:00:00", "vis": 1.5, "slp": 1014.7, "pod": "n", "dni": 0, "elev_angle": -41.34, "pres": 913.5, "h_angle": -90, "dewpt": 6.2, "snow": 0, "uv": 0, "solar_rad": 0, "wind_dir": 67, "weather": {"icon": "c04n", "code": 804, "description": "Overcast clouds"}, "ghi": 0, "dhi": 0, "timestamp_local": "2020-03-13T23:00:00", "app_temp": 5.6, "azimuth": 316.04, "datetime": "2020-03-13:22", "temp": 6.1, "precip": 0, "clouds": 100, "ts": 1584136800}, {"rh": 100, "wind_spd": 1.09069, "timestamp_utc": "2020-03-13T23:00:00", "vis": 1.5, "slp": 1014.7, "pod": "n", "dni": 0, "elev_angle": -47.62, "pres": 913.4, "h_angle": -90, "dewpt": 6.1, "snow": 0, "uv": 0, "solar_rad": 0, "wind_dir": 67, "weather": {"icon": "c04n", "code": 804, "description": "Overcast clouds"}, "ghi": 0, "dhi": 0, "timestamp_local": "2020-03-14T00:00:00", "app_temp": 5.7, "azimuth": 335.2, "datetime": "2020-03-13:23", "temp": 6, "precip": 0, "clouds": 99, "ts": 1584140400}], "sources": ["081170-99999", "imerg", "merra2", "era5", "modis"], "city_id": "3124783"}
{"timezone": "America/New_York", "state_code": "NC", "country_code": "US", "lat": 35.7721, "lon": -78.63861, "city_name": "Raleigh", "station_id": "723060-13722", "data": [{"rh": 65, "wind_spd": 2.1, "timestamp_utc": "2020-03-13T00:00:00", "vis": 1.5, "slp": 1014.1, "pod": "n", "dni": 0, "elev_angle": -8.83, "pres": 999.2, "h_angle": 75, "dewpt": 12.8, "snow": 0, "uv": 0, "solar_rad": 0, "wind_dir": 150, "weather": {"icon": "c02n", "code": 801, "description": "Few clouds"}, "ghi": 0, "dhi": 0, "timestamp_local": "2020-03-12T20:00:00", "app_temp": 19.1, "azimuth": 272.89, "datetime": "2020-03-13:00", "temp": 19.4, "precip": 0, "clouds": 18, "ts": 1584057600}, {"rh": 72, "wind_spd": 2.6, "timestamp_utc": "2020-03-13T01:00:00", "vis": 1, "slp": 1013.9, "pod": "n", "dni": 0, "elev_angle": -20.86, "pres": 999, "h_angle": 90, "dewpt": 13.3, "snow": 0, "uv": 0, "solar_rad": 0, "wind_dir": 130, "weather": {"icon": "c02n", "code": 802, "description": "Scattered clouds"}, "ghi": 0, "dhi": 0, "timestamp_local": "2020-03-12T21:00:00", "app_temp": 18.3, "azimuth": 282.16, "datetime": "2020-03-13:01", "temp": 18.3, "precip": 0, "clouds": 40, "ts": 1584061200}, {"rh": 72, "wind_spd": 2.6, "timestamp_utc": "2020-03-13T02:00:00", "vis": 5, "slp": 1014.4, "pod": "n", "dni": 0, "elev_angle": -32.43, "pres": 999.5, "h_angle": -90, "dewpt": 13.9, "snow": 0, "uv": 0, "solar_rad": 0, "wind_dir": 130, "weather": {"icon": "c04n", "code": 804, "description": "Overcast clouds"}, "ghi": 0, "dhi": 0, "timestamp_local": "2020-03-12T22:00:00", "app_temp": 18.7, "azimuth": 292.84, "datetime": "2020-03-13:02", "temp": 18.9, "precip": 0, "clouds": 100, "ts": 1584064800}, {"rh": 75, "wind_spd": 2.1, "timestamp_utc": "2020-03-13T03:00:00", "vis": 5, "slp": 1014.7, "pod": "n", "dni": 0, "elev_angle": -43, "pres": 999.8, "h_angle": -90, "dewpt": 14.4, "snow": 0, "uv": 0, "solar_rad": 0, "wind_dir": 150, "weather": {"icon": "c04n", "code": 804, "description": "Overcast clouds"}, "ghi": 0, "dhi": 0, "timestamp_local": "2020-03-12T23:00:00", "app_temp": 18.8, "azimuth": 306.34, "datetime": "2020-03-13:03", "temp": 18.9, "precip": 0, "clouds": 100, "ts": 1584068400}, {"rh": 69, "wind_spd": 3.6, "timestamp_utc": "2020-03-13T04:00:00", "vis": 5, "slp": 1013.9, "pod": "n", "dni": 0, "elev_angle": -51.54, "pres": 999, "h_angle": -90, "dewpt": 13.3, "snow": 0, "uv": 0, "solar_rad": 0, "wind_dir": 180, "weather": {"icon": "c04n", "code": 804, "description": "Overcast clouds"}, "ghi": 0, "dhi": 0, "timestamp_local": "2020-03-13T00:00:00", "app_temp": 18.6, "azimuth": 324.6, "datetime": "2020-03-13:04", "temp": 18.9, "precip": 0.5, "clouds": 81, "ts": 1584072000}, {"rh": 72, "wind_spd": 5.1, "timestamp_utc": "2020-03-13T05:00:00", "vis": 0.5, "slp": 1013.5, "pod": "n", "dni": 0, "elev_angle": -56.38, "pres": 998.6, "h_angle": -90, "dewpt": 13.9, "snow": 0, "uv": 0, "solar_rad": 0, "wind_dir": 190, "weather": {"icon": "c03n", "code": 803, "description": "Broken clouds"}, "ghi": 0, "dhi": 0, "timestamp_local": "2020-03-13T01:00:00", "app_temp": 18.7, "azimuth": 348.87, "datetime": "2020-03-13:05", "temp": 18.9, "precip": 0.2, "clouds": 66, "ts": 1584075600}, {"rh": 81, "wind_spd": 4.1, "timestamp_utc": "2020-03-13T06:00:00", "vis": 5, "slp": 1013.4, "pod": "n", "dni": 0, "elev_angle": -55.85, "pres": 998.5, "h_angle": -90, "dewpt": 15.6, "snow": 0, "uv": 0, "solar_rad": 0, "wind_dir": 210, "weather": {"icon": "c04n", "code": 804, "description": "Overcast clouds"}, "ghi": 0, "dhi": 0, "timestamp_local": "2020-03-13T02:00:00", "app_temp": 19, "azimuth": 15.91, "datetime": "2020-03-13:06", "temp": 18.9, "precip": 0, "clouds": 100, "ts": 1584079200}, {"rh": 81, "wind_spd": 5.7, "timestamp_utc": "2020-03-13T07:00:00", "vis": 5, "slp": 1013.1, "pod": "n", "dni": 0, "elev_angle": -50.17, "pres": 998.2, "h_angle": -90, "dewpt": 15.6, "snow": 0, "uv": 0, "solar_rad": 0, "wind_dir": 210, "weather": {"icon": "c04n", "code": 804, "description": "Overcast clouds"}, "ghi": 0, "dhi": 0, "timestamp_local": "2020-03-13T03:00:00", "app_temp": 19, "azimuth": 39.12, "datetime": "2020-03-13:07", "temp": 18.9, "precip": 0, "clouds": 100, "ts": 1584082800}, {"rh": 81, "wind_spd": 5.7, "timestamp_utc": "2020-03-13T08:00:00", "vis": 5, "slp": 1013.3, "pod": "n", "dni": 0, "elev_angle": -41.13, "pres": 998.4, "h_angle": -90, "dewpt": 15.6, "snow": 0, "uv": 0, "solar_rad": 0, "wind_dir": 220, "weather": {"icon": "r01n", "code": 500, "description": "Light rain"}, "ghi": 0, "dhi": 0, "timestamp_local": "2020-03-13T04:00:00", "app_temp": 19, "azimuth": 56.32, "datetime": "2020-03-13:08", "temp": 18.9, "precip": 0.7, "clouds": 100, "ts": 1584086400}, {"rh": 84, "wind_spd": 6.2, "timestamp_utc": "2020-03-13T09:00:00", "vis": 5, "slp": 1012.7, "pod": "n", "dni": 0, "elev_angle": -30.31, "pres": 997.8, "h_angle": -90, "dewpt": 15.6, "snow": 0, "uv": 0, "solar_rad": 0, "wind_dir": 210, "weather": {"icon": "r01n", "code": 500, "description": "Light rain"}, "ghi": 0, "dhi": 0, "timestamp_local": "2020-03-13T05:00:00", "app_temp": 18.3, "azimuth": 69.15, "datetime": "2020-03-13:09", "temp": 18.3, "precip": 0.7, "clouds": 100, "ts": 1584090000}, {"rh": 89, "wind_spd": 5.1, "timestamp_utc": "2020-03-13T10:00:00", "vis": 5, "slp": 1012.7, "pod": "n", "dni": 0, "elev_angle": -18.61, "pres": 997.7, "h_angle": -90, "dewpt": 16.1, "snow": 0, "uv": 0, "solar_rad": 0, "wind_dir": 200, "weather": {"icon": "r01n", "code": 500, "description": "Light rain"}, "ghi": 0, "dhi": 0, "timestamp_local": "2020-03-13T06:00:00", "app_temp": 17.8, "azimuth": 79.47, "datetime": "2020-03-13:10", "temp": 17.8, "precip": 1.1, "clouds": 100, "ts": 1584093600}, {"rh": 84, "wind_spd": 6.7, "timestamp_utc": "2020-03-13T11:00:00", "vis": 5, "slp": 1013.3, "pod": "n", "dni": 0, "elev_angle": -6.52, "pres": 998.4, "h_angle": -90, "dewpt": 15.6, "snow": 0, "uv": 0, "solar_rad": 0, "wind_dir": 210, "weather": {"icon": "c04n", "code": 804, "description": "Overcast clouds"}, "ghi": 0, "dhi": 0, "timestamp_local": "2020-03-13T07:00:00", "app_temp": 18.3, "azimuth": 88.56, "datetime": "2020-03-13:11", "temp": 18.3, "precip": 0.5, "clouds": 100, "ts": 1584097200}, {"rh": 86, "wind_spd": 6.2, "timestamp_utc": "2020-03-13T12:00:00", "vis": 5, "slp": 1013.7, "pod": "d", "dni": 326.77, "elev_angle": 5.62, "pres": 998.7, "h_angle": -90, "dewpt": 15.6, "snow": 0, "uv": 0.9, "solar_rad": 17.7867, "wind_dir": 210, "weather": {"icon": "c04d", "code": 804, "description": "Overcast clouds"}, "ghi": 60.3, "dhi": 37.69, "timestamp_local": "2020-03-13T08:00:00", "app_temp": 17.8, "azimuth": 97.38, "datetime": "2020-03-13:12", "temp": 17.8, "precip": 0, "clouds": 96, "ts": 1584100800}, {"rh": 89, "wind_spd": 6.7, "timestamp_utc": "2020-03-13T13:00:00", "vis": 5, "slp": 1014.7, "pod": "d", "dni": 643.73, "elev_angle": 17.5, "pres": 999.7, "h_angle": -75, "dewpt": 16.1, "snow": 0, "uv": 1.3, "solar_rad": 95.2031, "wind_dir": 220, "weather": {"icon": "c04d", "code": 804, "description": "Overcast clouds"}, "ghi": 259.33, "dhi": 72.94, "timestamp_local": "2020-03-13T09:00:00", "app_temp": 17.8, "azimuth": 106.71, "datetime": "2020-03-13:13", "temp": 17.8, "precip": 0.1, "clouds": 93, "ts": 1584104400}, {"rh": 89, "wind_spd": 4.1, "timestamp_utc": "2020-03-13T14:00:00", "vis": 0.5, "slp": 1014.8, "pod": "d", "dni": 780.92, "elev_angle": 28.77, "pres": 999.8, "h_angle": -60, "dewpt": 16.1, "snow": 0, "uv": 2.6, "solar_rad": 351.126, "wind_dir": 230, "weather": {"icon": "c03d", "code": 803, "description": "Broken clouds"}, "ghi": 462.55, "dhi": 93.16, "timestamp_local": "2020-03-13T10:00:00", "app_temp": 17.8, "azimuth": 117.49, "datetime": "2020-03-13:14", "temp": 17.8, "precip": 0.4, "clouds": 70, "ts": 1584108000}, {"rh": 84, "wind_spd": 5.7, "timestamp_utc": "2020-03-13T15:00:00", "vis": 5, "slp": 1015.2, "pod": "d", "dni": 855.05, "elev_angle": 38.85, "pres": 1000.3, "h_angle": -60, "dewpt": 16.7, "snow": 0, "uv": 2, "solar_rad": 120.775, "wind_dir": 230, "weather": {"icon": "r01d", "code": 500, "description": "Light rain"}, "ghi": 635.66, "dhi": 106.04, "timestamp_local": "2020-03-13T11:00:00", "app_temp": 19.6, "azimuth": 130.89, "datetime": "2020-03-13:15", "temp": 19.4, "precip": 2.3, "clouds": 100, "ts": 1584111600}, {"rh": 75, "wind_spd": 4.6, "timestamp_utc": "2020-03-13T16:00:00", "vis": 5, "slp": 1015.8, "pod": "d", "dni": 895.55, "elev_angle": 46.77, "pres": 1001, "h_angle": -45, "dewpt": 16.7, "snow": 0, "uv": 2.7, "solar_rad": 280.899, "wind_dir": 230, "weather": {"icon": "c04d", "code": 804, "description": "Overcast clouds"}, "ghi": 759.13, "dhi": 113.8, "timestamp_local": "2020-03-13T12:00:00", "app_temp": 21.2, "azimuth": 148.31, "datetime": "2020-03-13:16", "temp": 21.1, "precip": 0, "clouds": 95, "ts": 1584115200}, {"rh": 73, "wind_spd": 4.1, "timestamp_utc": "2020-03-13T17:00:00", "vis": 5, "slp": 1016.4, "pod": "d", "dni": 913.08, "elev_angle": 51.12, "pres": 1001.6, "h_angle": -15, "dewpt": 16.7, "snow": 0, "uv": 2.6, "solar_rad": 205.173, "wind_dir": 240, "weather": {"icon": "c04d", "code": 804, "description": "Overcast clouds"}, "ghi": 820.69, "dhi": 117.34, "timestamp_local": "2020-03-13T13:00:00", "app_temp": 21.8, "azimuth": 170.25, "datetime": "2020-03-13:17", "temp": 21.7, "precip": 0.3, "clouds": 100, "ts": 1584118800}, {"rh": 70, "wind_spd": 5.7, "timestamp_utc": "2020-03-13T18:00:00", "vis": 5, "slp": 1015.6, "pod": "d", "dni": 911.39, "elev_angle": 50.67, "pres": 1000.9, "h_angle": 0, "dewpt": 17.2, "snow": 0, "uv": 2.6, "solar_rad": 203.635, "wind_dir": 230, "weather": {"icon": "c04d", "code": 804, "description": "Overcast clouds"}, "ghi": 814.54, "dhi": 117, "timestamp_local": "2020-03-13T14:00:00", "app_temp": 23, "azimuth": 194.11, "datetime": "2020-03-13:18", "temp": 22.8, "precip": 0.4, "clouds": 100, "ts": 1584122400}, {"rh": 61, "wind_spd": 2.6, "timestamp_utc": "2020-03-13T19:00:00", "vis": 5, "slp": 1015.7, "pod": "d", "dni": 890.16, "elev_angle": 45.57, "pres": 1001, "h_angle": 15, "dewpt": 15.6, "snow": 0, "uv": 2.9, "solar_rad": 367.186, "wind_dir": 260, "weather": {"icon": "c04d", "code": 804, "description": "Overcast clouds"}, "ghi": 741.26, "dhi": 112.73, "timestamp_local": "2020-03-13T15:00:00", "app_temp": 23.3, "azimuth": 215.32, "datetime": "2020-03-13:19", "temp": 23.3, "precip": 0, "clouds": 89, "ts": 1584126000}, {"rh": 57, "wind_spd": 4.1, "timestamp_utc": "2020-03-13T20:00:00", "vis": 5, "slp": 1016, "pod": "d", "dni": 844.72, "elev_angle": 37.17, "pres": 1001.3, "h_angle": 30, "dewpt": 14.4, "snow": 0, "uv": 2.1, "solar_rad": 196.809, "wind_dir": 260, "weather": {"icon": "c04d", "code": 804, "description": "Overcast clouds"}, "ghi": 607.84, "dhi": 104.14, "timestamp_local": "2020-03-13T16:00:00", "app_temp": 23.2, "azimuth": 231.94, "datetime": "2020-03-13:20", "temp": 23.3, "precip": 0, "clouds": 97, "ts": 1584129600}, {"rh": 57, "wind_spd": 3.6, "timestamp_utc": "2020-03-13T21:00:00", "vis": 5, "slp": 1016.4, "pod": "d", "dni": 762.45, "elev_angle": 26.82, "pres": 1001.6, "h_angle": 45, "dewpt": 13.3, "snow": 0, "uv": 1.5, "solar_rad": 106.933, "wind_dir": 260, "weather": {"icon": "c04d", "code": 804, "description": "Overcast clouds"}, "ghi": 427.73, "dhi": 90.19, "timestamp_local": "2020-03-13T17:00:00", "app_temp": 22, "azimuth": 244.77, "datetime": "2020-03-13:21", "temp": 22.2, "precip": 0, "clouds": 100, "ts": 1584133200}, {"rh": 55, "wind_spd": 2.6, "timestamp_utc": "2020-03-13T22:00:00", "vis": 5, "slp": 1016.9, "pod": "d", "dni": 607.22, "elev_angle": 15.42, "pres": 1002.1, "h_angle": 60, "dewpt": 13.3, "snow": 0, "uv": 1.2, "solar_rad": 82.1942, "wind_dir": 280, "weather": {"icon": "c04d", "code": 804, "description": "Overcast clouds"}, "ghi": 222.13, "dhi": 68.19, "timestamp_local": "2020-03-13T18:00:00", "app_temp": 22.6, "azimuth": 255.23, "datetime": "2020-03-13:22", "temp": 22.8, "precip": 0, "clouds": 95, "ts": 1584136800}, {"rh": 59, "wind_spd": 2.1, "timestamp_utc": "2020-03-13T23:00:00", "vis": 5, "slp": 1017.4, "pod": "n", "dni": 218.82, "elev_angle": 3.48, "pres": 1002.6, "h_angle": 60, "dewpt": 13.9, "snow": 0, "uv": 1, "solar_rad": 16.8604, "wind_dir": 260, "weather": {"icon": "c04n", "code": 804, "description": "Overcast clouds"}, "ghi": 31.64, "dhi": 27.73, "timestamp_local": "2020-03-13T19:00:00", "app_temp": 22, "azimuth": 264.43, "datetime": "2020-03-13:23", "temp": 22.2, "precip": 0.1, "clouds": 87, "ts": 1584140400}], "sources": ["723060-13722", "imerg", "merra2", "era5", "modis"], "city_id": "4487042"}
